pz_rail_som-1.1.3.dist-info/licenses/LICENSE
rail/creation/degraders/specz_som.py
rail/estimation/algos/minisom_som.py
rail/estimation/algos/somoclu_som.py
rail/som/__init__.py
rail/som/_version.py
pz_rail_som-1.1.3.dist-info/METADATA
pz_rail_som-1.1.3.dist-info/WHEEL
pz_rail_som-1.1.3.dist-info/top_level.txt
pz_rail_som-1.1.3.dist-info/RECORD
