Metadata-Version: 2.4
Name: pz-rail-som
Version: 1.1.3
Author-email: "LSST Dark Energy Science Collaboration (DESC)" <later@later.com>
License: MIT License
Classifier: Development Status :: 4 - Beta
Classifier: License :: OSI Approved :: MIT License
Classifier: Intended Audience :: Developers
Classifier: Intended Audience :: Science/Research
Classifier: Operating System :: OS Independent
Classifier: Programming Language :: Python
Requires-Python: >=3.9
License-File: LICENSE
Requires-Dist: deprecated
Requires-Dist: pandas
Requires-Dist: pz-rail-base>=1.0.3
Requires-Dist: scikit-learn
Requires-Dist: minisom
Requires-Dist: somoclu
Provides-Extra: dev
Requires-Dist: qp-prob[full]; extra == "dev"
Requires-Dist: pytest; extra == "dev"
Requires-Dist: pytest-cov; extra == "dev"
Requires-Dist: pre-commit; extra == "dev"
Requires-Dist: pylint; extra == "dev"
Dynamic: license-file
